pycolorbar/__init__.py
pycolorbar/_version.py
pycolorbar/bivariate/__init__.py
pycolorbar/bivariate/cmap.py
pycolorbar/bivariate/data/bremm.npy
pycolorbar/bivariate/data/cubediagonal.npy
pycolorbar/bivariate/data/schumann.npy
pycolorbar/bivariate/data/steiger.npy
pycolorbar/bivariate/data/teuling2.npy
pycolorbar/bivariate/data/ziegler.npy
pycolorbar/colors/__init__.py
pycolorbar/colors/colors_io.py
pycolorbar/etc/colorbars/example_colorbar_configurations.yaml
pycolorbar/etc/colormaps/cmasher/amber.yaml
pycolorbar/etc/colormaps/cmasher/amethyst.yaml
pycolorbar/etc/colormaps/cmasher/apple.yaml
pycolorbar/etc/colormaps/cmasher/arctic.yaml
pycolorbar/etc/colormaps/cmasher/bubblegum.yaml
pycolorbar/etc/colormaps/cmasher/chroma.yaml
pycolorbar/etc/colormaps/cmasher/copper.yaml
pycolorbar/etc/colormaps/cmasher/copper_s.yaml
pycolorbar/etc/colormaps/cmasher/cosmic.yaml
pycolorbar/etc/colormaps/cmasher/dusk.yaml
pycolorbar/etc/colormaps/cmasher/eclipse.yaml
pycolorbar/etc/colormaps/cmasher/ember.yaml
pycolorbar/etc/colormaps/cmasher/emerald.yaml
pycolorbar/etc/colormaps/cmasher/emergency.yaml
pycolorbar/etc/colormaps/cmasher/emergency_s.yaml
pycolorbar/etc/colormaps/cmasher/fall.yaml
pycolorbar/etc/colormaps/cmasher/flamingo.yaml
pycolorbar/etc/colormaps/cmasher/freeze.yaml
pycolorbar/etc/colormaps/cmasher/fusion.yaml
pycolorbar/etc/colormaps/cmasher/gem.yaml
pycolorbar/etc/colormaps/cmasher/ghostlight.yaml
pycolorbar/etc/colormaps/cmasher/gothic.yaml
pycolorbar/etc/colormaps/cmasher/guppy.yaml
pycolorbar/etc/colormaps/cmasher/holly.yaml
pycolorbar/etc/colormaps/cmasher/horizon.yaml
pycolorbar/etc/colormaps/cmasher/iceburn.yaml
pycolorbar/etc/colormaps/cmasher/infinity.yaml
pycolorbar/etc/colormaps/cmasher/infinity_s.yaml
pycolorbar/etc/colormaps/cmasher/jungle.yaml
pycolorbar/etc/colormaps/cmasher/lavender.yaml
pycolorbar/etc/colormaps/cmasher/lilac.yaml
pycolorbar/etc/colormaps/cmasher/neon.yaml
pycolorbar/etc/colormaps/cmasher/neutral.yaml
pycolorbar-0.1.3.dist-info/licenses/LICENSE
pycolorbar-0.1.3.dist-info/METADATA
pycolorbar-0.1.3.dist-info/WHEEL
pycolorbar-0.1.3.dist-info/top_level.txt
pycolorbar-0.1.3.dist-info/RECORD
