Metadata-Version: 2.4
Name: pycolorbar
Version: 0.1.3
Summary: YAML-based colormap & colorbar settings for matplotlib and xarray
Author-email: Gionata Ghiggi <gionata.ghiggi@epfl.ch>
License: MIT License
Project-URL: Homepage, https://github.com/ghiggi/pycolorbar
Project-URL: Source, https://github.com/ghiggi/pycolorbar
Project-URL: Tracker, https://github.com/ghiggi/pycolorbar/issues
Project-URL: Documentation, https://pycolorbar.readthedocs.io
Project-URL: changelog, https://github.com/ghiggi/pycolorbar/CHANGELOG.md
Keywords: colormap,colorbar,bivariate,trivariate
Classifier: Development Status :: 2 - Pre-Alpha
Classifier: Intended Audience :: Science/Research
Classifier: Intended Audience :: Education
Classifier: License :: OSI Approved :: MIT License
Classifier: Natural Language :: English
Classifier: Operating System :: OS Independent
Classifier: Operating System :: Unix
Classifier: Operating System :: Microsoft
Classifier: Operating System :: MacOS
Classifier: Programming Language :: Python
Classifier: Programming Language :: Python :: 3
Classifier: Programming Language :: Python :: 3 :: Only
Classifier: Programming Language :: Python :: 3.11
Classifier: Programming Language :: Python :: 3.12
Classifier: Programming Language :: Python :: 3.13
Classifier: Programming Language :: Python :: 3.14
Classifier: Topic :: Scientific/Engineering
Classifier: Topic :: Scientific/Engineering :: Image Processing
Requires-Python: >=3.11
License-File: LICENSE
Requires-Dist: matplotlib
Requires-Dist: numpy
Requires-Dist: pydantic>=2.0.0
Requires-Dist: PyYAML
Provides-Extra: dev
Requires-Dist: pre-commit; extra == "dev"
Requires-Dist: loghub; extra == "dev"
Requires-Dist: deepdiff; extra == "dev"
Requires-Dist: pytest; extra == "dev"
Requires-Dist: pytest-cov; extra == "dev"
Requires-Dist: pytest-mock; extra == "dev"
Requires-Dist: pytest-sugar; extra == "dev"
Requires-Dist: setuptools; extra == "dev"
Requires-Dist: build; extra == "dev"
Requires-Dist: twine; extra == "dev"
Dynamic: license-file
